pydipole/__init__.py
pydipole/__main__.py
pydipole/_version.py
pydipole/periodic.py
pydipole/utils.py
pydipole/data/database.csv
pydipole/data/references.bib
pydipole-0.0.1.dist-info/METADATA
pydipole-0.0.1.dist-info/WHEEL
pydipole-0.0.1.dist-info/entry_points.txt
pydipole-0.0.1.dist-info/top_level.txt
pydipole-0.0.1.dist-info/RECORD
