Metadata-Version: 2.1
Name: pydipole
Version: 0.0.1
Summary: Table of dipole polarizaility for atom with Z=1 to 120 
Author-email: YingXing Cheng <yingxing.cheng@ugent.be>
Maintainer-email: YingXing Cheng <yxcheng2buaa@gmail.com>
Project-URL: Homepage, https://github.com/AtomPolarTable/dipole-polarizability
Project-URL: Repository, https://github.com/AtomPolarTable/dipole-polarizability
Project-URL: Changelog, https://github.com/AtomPolarTable/dipole-polarizability/CHANGELOG.md
Keywords: dipole polarizability,periodic table
Classifier: Development Status :: 3 - Alpha
Classifier: Environment :: Console
Classifier: Intended Audience :: Science/Research
Classifier: Intended Audience :: Education
Classifier: Framework :: Matplotlib
Classifier: License :: OSI Approved :: GNU General Public License v3 or later (GPLv3+)
Classifier: Natural Language :: English
Classifier: Operating System :: POSIX
Classifier: Operating System :: MacOS
Classifier: Operating System :: Microsoft :: Windows
Classifier: Programming Language :: Python :: 3
Classifier: Topic :: Scientific/Engineering
Requires-Python: >=3.8
Requires-Dist: pandas
Requires-Dist: importlib-resources
Requires-Dist: jinja2
Provides-Extra: dev
Requires-Dist: pre-commit ; extra == 'dev'
Provides-Extra: tests
Requires-Dist: pytest ; extra == 'tests'
